{"householdId": "77", "familyName": "Graveston", "trace": [{"sequence": 19730, "action": "Add Entity", "element": "classOfAssistance (ClassOfAssistance) [29]", "oldValue": "", "newValue": "", "associationEntity": null, "location": "Medicaid Coverage Options : 1", "entityName": "classOfAssistance", "entityType": "ClassOfAssistance", "entityId": 29, "attributeName": null, "associationEntityName": null, "associationEntityType": null, "associationEntityId": null, "rulesheetName": "Medicaid Coverage Options", "ruleNumber": "1", "householdId": "77", "familyName": "Graveston", "personId": 273, "personName": "Marti Graveston", "coaName": "Supplemental Security Income (SSI) Medicaid", "policyKey": "GA_SSI_MEDICAID"}, {"sequence": 19731, "action": "Update Attribute", "element": "classOfAssistance (ClassOfAssistance) [29]/requiresMedicaidIneligibility", "oldValue": "", "newValue": "false", "associationEntity": null, "location": "Medicaid Coverage Options : 1", "entityName": "classOfAssistance", "entityType": "ClassOfAssistance", "entityId": 29, "attributeName": "requiresMedicaidIneligibility", "associationEntityName": null, "associationEntityType": null, "associationEntityId": null, "rulesheetName": "Medicaid Coverage Options", "ruleNumber": "1", "householdId": "77", "familyName": "Graveston", "personId": 273, "personName": "Marti Graveston", "coaName": "Supplemental Security Income (SSI) Medicaid", "policyKey": "GA_SSI_MEDICAID"}, {"sequence": 19732, "action": "Update Attribute", "element": "classOfAssistance (ClassOfAssistance) [29]/programFamily", "oldValue": "", "newValue": "Medicaid", "associationEntity": null, "location": "Medicaid Coverage Options : 1", "entityName": "classOfAssistance", "entityType": "ClassOfAssistance", "entityId": 29, "attributeName": "programFamily", "associationEntityName": null, "associationEntityType": null, "associationEntityId": null, "rulesheetName": "Medicaid Coverage Options", "ruleNumber": "1", "householdId": "77", "familyName": "Graveston", "personId": 273, "personName": "Marti Graveston", "coaName": "Supplemental Security Income (SSI) Medicaid", "policyKey": "GA_SSI_MEDICAID"}, {"sequence": 19733, "action": "Update Attribute", "element": "classOfAssistance (ClassOfAssistance) [29]/policyKey", "oldValue": "", "newValue": "GA_SSI_MEDICAID", "associationEntity": null, "location": "Medicaid Coverage Options : 1", "entityName": "classOfAssistance", "entityType": "ClassOfAssistance", "entityId": 29, "attributeName": "policyKey", "associationEntityName": null, "associationEntityType": null, "associationEntityId": null, "rulesheetName": "Medicaid Coverage Options", "ruleNumber": "1", "householdId": "77", "familyName": "Graveston", "personId": 273, "personName": "Marti Graveston", "coaName": "Supplemental Security Income (SSI) Medicaid", "policyKey": "GA_SSI_MEDICAID"}, {"sequence": 19734, "action": "Update Attribute", "element": "classOfAssistance (ClassOfAssistance) [29]/nonFinancialCriteriaMet", "oldValue": "", "newValue": "true", "associationEntity": null, "location": "Medicaid Coverage Options : 1", "entityName": "classOfAssistance", "entityType": "ClassOfAssistance", "entityId": 29, "attributeName": "nonFinancialCriteriaMet", "associationEntityName": null, "associationEntityType": null, "associationEntityId": null, "rulesheetName": "Medicaid Coverage Options", "ruleNumber": "1", "householdId": "77", "familyName": "Graveston", "personId": 273, "personName": "Marti Graveston", "coaName": "Supplemental Security Income (SSI) Medicaid", "policyKey": "GA_SSI_MEDICAID"}, {"sequence": 20630, "action": "Add Entity", "element": "classOfAssistance (ClassOfAssistance) [179]", "oldValue": "", "newValue": "", "associationEntity": null, "location": "Medicaid Coverage Options : 2", "entityName": "classOfAssistance", "entityType": "ClassOfAssistance", "entityId": 179, "attributeName": null, "associationEntityName": null, "associationEntityType": null, "associationEntityId": null, "rulesheetName": "Medicaid Coverage Options", "ruleNumber": "2", "householdId": "77", "familyName": "Graveston", "personId": 273, "personName": "Marti Graveston", "coaName": "Pickle", "policyKey": "GA_PICKLE"}, {"sequence": 20631, "action": "Update Attribute", "element": "classOfAssistance (ClassOfAssistance) [179]/requiresMedicaidIneligibility", "oldValue": "", "newValue": "false", "associationEntity": null, "location": "Medicaid Coverage Options : 2", "entityName": "classOfAssistance", "entityType": "ClassOfAssistance", "entityId": 179, "attributeName": "requiresMedicaidIneligibility", "associationEntityName": null, "associationEntityType": null, "associationEntityId": null, "rulesheetName": "Medicaid Coverage Options", "ruleNumber": "2", "householdId": "77", "familyName": "Graveston", "personId": 273, "personName": "Marti Graveston", "coaName": "Pickle", "policyKey": "GA_PICKLE"}, {"sequence": 20632, "action": "Update Attribute", "element": "classOfAssistance (ClassOfAssistance) [179]/programFamily", "oldValue": "", "newValue": "Medicaid", "associationEntity": null, "location": "Medicaid Coverage Options : 2", "entityName": "classOfAssistance", "entityType": "ClassOfAssistance", "entityId": 179, "attributeName": "programFamily", "associationEntityName": null, "associationEntityType": null, "associationEntityId": null, "rulesheetName": "Medicaid Coverage Options", "ruleNumber": "2", "householdId": "77", "familyName": "Graveston", "personId": 273, "personName": "Marti Graveston", "coaName": "Pickle", "policyKey": "GA_PICKLE"}, {"sequence": 20633, "action": "Update Attribute", "element": "classOfAssistance (ClassOfAssistance) [179]/policyKey", "oldValue": "", "newValue": "GA_PICKLE", "associationEntity": null, "location": "Medicaid Coverage Options : 2", "entityName": "classOfAssistance", "entityType": "ClassOfAssistance", "entityId": 179, "attributeName": "policyKey", "associationEntityName": null, "associationEntityType": null, "associationEntityId": null, "rulesheetName": "Medicaid Coverage Options", "ruleNumber": "2", "householdId": "77", "familyName": "Graveston", "personId": 273, "personName": "Marti Graveston", "coaName": "Pickle", "policyKey": "GA_PICKLE"}, {"sequence": 20634, "action": "Update Attribute", "element": "classOfAssistance (ClassOfAssistance) [179]/nonFinancialCriteriaMet", "oldValue": "", "newValue": "true", "associationEntity": null, "location": "Medicaid Coverage Options : 2", "entityName": "classOfAssistance", "entityType": "ClassOfAssistance", "entityId": 179, "attributeName": "nonFinancialCriteriaMet", "associationEntityName": null, "associationEntityType": null, "associationEntityId": null, "rulesheetName": "Medicaid Coverage Options", "ruleNumber": "2", "householdId": "77", "familyName": "Graveston", "personId": 273, "personName": "Marti Graveston", "coaName": "Pickle", "policyKey": "GA_PICKLE"}, {"sequence": 21146, "action": "Add Entity", "element": "classOfAssistance (ClassOfAssistance) [265]", "oldValue": "", "newValue": "", "associationEntity": null, "location": "Medicaid Coverage Options : 8", "entityName": "classOfAssistance", "entityType": "ClassOfAssistance", "entityId": 265, "attributeName": null, "associationEntityName": null, "associationEntityType": null, "associationEntityId": null, "rulesheetName": "Medicaid Coverage Options", "ruleNumber": "8", "householdId": "77", "familyName": "Graveston", "personId": 273, "personName": "Marti Graveston", "coaName": "Protected Medicaid 1972", "policyKey": "GA_PROTECTED_MEDICAID_1972"}, {"sequence": 21147, "action": "Update Attribute", "element": "classOfAssistance (ClassOfAssistance) [265]/requiresMedicaidIneligibility", "oldValue": "", "newValue": "false", "associationEntity": null, "location": "Medicaid Coverage Options : 8", "entityName": "classOfAssistance", "entityType": "ClassOfAssistance", "entityId": 265, "attributeName": "requiresMedicaidIneligibility", "associationEntityName": null, "associationEntityType": null, "associationEntityId": null, "rulesheetName": "Medicaid Coverage Options", "ruleNumber": "8", "householdId": "77", "familyName": "Graveston", "personId": 273, "personName": "Marti Graveston", "coaName": "Protected Medicaid 1972", "policyKey": "GA_PROTECTED_MEDICAID_1972"}, {"sequence": 21148, "action": "Update Attribute", "element": "classOfAssistance (ClassOfAssistance) [265]/programFamily", "oldValue": "", "newValue": "Medicaid", "associationEntity": null, "location": "Medicaid Coverage Options : 8", "entityName": "classOfAssistance", "entityType": "ClassOfAssistance", "entityId": 265, "attributeName": "programFamily", "associationEntityName": null, "associationEntityType": null, "associationEntityId": null, "rulesheetName": "Medicaid Coverage Options", "ruleNumber": "8", "householdId": "77", "familyName": "Graveston", "personId": 273, "personName": "Marti Graveston", "coaName": "Protected Medicaid 1972", "policyKey": "GA_PROTECTED_MEDICAID_1972"}, {"sequence": 21149, "action": "Update Attribute", "element": "classOfAssistance (ClassOfAssistance) [265]/policyKey", "oldValue": "", "newValue": "GA_PROTECTED_MEDICAID_1972", "associationEntity": null, "location": "Medicaid Coverage Options : 8", "entityName": "classOfAssistance", "entityType": "ClassOfAssistance", "entityId": 265, "attributeName": "policyKey", "associationEntityName": null, "associationEntityType": null, "associationEntityId": null, "rulesheetName": "Medicaid Coverage Options", "ruleNumber": "8", "householdId": "77", "familyName": "Graveston", "personId": 273, "personName": "Marti Graveston", "coaName": "Protected Medicaid 1972", "policyKey": "GA_PROTECTED_MEDICAID_1972"}, {"sequence": 21150, "action": "Update Attribute", "element": "classOfAssistance (ClassOfAssistance) [265]/nonFinancialCriteriaMet", "oldValue": "", "newValue": "true", "associationEntity": null, "location": "Medicaid Coverage Options : 8", "entityName": "classOfAssistance", "entityType": "ClassOfAssistance", "entityId": 265, "attributeName": "nonFinancialCriteriaMet", "associationEntityName": null, "associationEntityType": null, "associationEntityId": null, "rulesheetName": "Medicaid Coverage Options", "ruleNumber": "8", "householdId": "77", "familyName": "Graveston", "personId": 273, "personName": "Marti Graveston", "coaName": "Protected Medicaid 1972", "policyKey": "GA_PROTECTED_MEDICAID_1972"}, {"sequence": 22334, "action": "Add Entity", "element": "classOfAssistance (ClassOfAssistance) [463]", "oldValue": "", "newValue": "", "associationEntity": null, "location": "Medicaid Coverage Options : 21", "entityName": "classOfAssistance", "entityType": "ClassOfAssistance", "entityId": 463, "attributeName": null, "associationEntityName": null, "associationEntityType": null, "associationEntityId": null, "rulesheetName": "Medicaid Coverage Options", "ruleNumber": "21", "householdId": "77", "familyName": "Graveston", "personId": 273, "personName": "Marti Graveston", "coaName": "ABD Medically Needy", "policyKey": "GA_ABD_MED_NEEDY"}, {"sequence": 22335, "action": "Update Attribute", "element": "classOfAssistance (ClassOfAssistance) [463]/requiresMedicaidIneligibility", "oldValue": "", "newValue": "false", "associationEntity": null, "location": "Medicaid Coverage Options : 21", "entityName": "classOfAssistance", "entityType": "ClassOfAssistance", "entityId": 463, "attributeName": "requiresMedicaidIneligibility", "associationEntityName": null, "associationEntityType": null, "associationEntityId": null, "rulesheetName": "Medicaid Coverage Options", "ruleNumber": "21", "householdId": "77", "familyName": "Graveston", "personId": 273, "personName": "Marti Graveston", "coaName": "ABD Medically Needy", "policyKey": "GA_ABD_MED_NEEDY"}, {"sequence": 22336, "action": "Update Attribute", "element": "classOfAssistance (ClassOfAssistance) [463]/programFamily", "oldValue": "", "newValue": "Medicaid", "associationEntity": null, "location": "Medicaid Coverage Options : 21", "entityName": "classOfAssistance", "entityType": "ClassOfAssistance", "entityId": 463, "attributeName": "programFamily", "associationEntityName": null, "associationEntityType": null, "associationEntityId": null, "rulesheetName": "Medicaid Coverage Options", "ruleNumber": "21", "householdId": "77", "familyName": "Graveston", "personId": 273, "personName": "Marti Graveston", "coaName": "ABD Medically Needy", "policyKey": "GA_ABD_MED_NEEDY"}, {"sequence": 22337, "action": "Update Attribute", "element": "classOfAssistance (ClassOfAssistance) [463]/policyKey", "oldValue": "", "newValue": "GA_ABD_MED_NEEDY", "associationEntity": null, "location": "Medicaid Coverage Options : 21", "entityName": "classOfAssistance", "entityType": "ClassOfAssistance", "entityId": 463, "attributeName": "policyKey", "associationEntityName": null, "associationEntityType": null, "associationEntityId": null, "rulesheetName": "Medicaid Coverage Options", "ruleNumber": "21", "householdId": "77", "familyName": "Graveston", "personId": 273, "personName": "Marti Graveston", "coaName": "ABD Medically Needy", "policyKey": "GA_ABD_MED_NEEDY"}, {"sequence": 22338, "action": "Update Attribute", "element": "classOfAssistance (ClassOfAssistance) [463]/nonFinancialCriteriaMet", "oldValue": "", "newValue": "true", "associationEntity": null, "location": "Medicaid Coverage Options : 21", "entityName": "classOfAssistance", "entityType": "ClassOfAssistance", "entityId": 463, "attributeName": "nonFinancialCriteriaMet", "associationEntityName": null, "associationEntityType": null, "associationEntityId": null, "rulesheetName": "Medicaid Coverage Options", "ruleNumber": "21", "householdId": "77", "familyName": "Graveston", "personId": 273, "personName": "Marti Graveston", "coaName": "ABD Medically Needy", "policyKey": "GA_ABD_MED_NEEDY"}, {"sequence": 27734, "action": "Add Entity", "element": "classOfAssistance (ClassOfAssistance) [1363]", "oldValue": "", "newValue": "", "associationEntity": null, "location": "Medicaid Coverage Options : 28", "entityName": "classOfAssistance", "entityType": "ClassOfAssistance", "entityId": 1363, "attributeName": null, "associationEntityName": null, "associationEntityType": null, "associationEntityId": null, "rulesheetName": "Medicaid Coverage Options", "ruleNumber": "28", "householdId": "77", "familyName": "Graveston", "personId": 273, "personName": "Marti Graveston", "coaName": "Pregnant Women", "policyKey": "GA_PREGNANT_MEDICAID"}, {"sequence": 27735, "action": "Update Attribute", "element": "classOfAssistance (ClassOfAssistance) [1363]/requiresMedicaidIneligibility", "oldValue": "", "newValue": "false", "associationEntity": null, "location": "Medicaid Coverage Options : 28", "entityName": "classOfAssistance", "entityType": "ClassOfAssistance", "entityId": 1363, "attributeName": "requiresMedicaidIneligibility", "associationEntityName": null, "associationEntityType": null, "associationEntityId": null, "rulesheetName": "Medicaid Coverage Options", "ruleNumber": "28", "householdId": "77", "familyName": "Graveston", "personId": 273, "personName": "Marti Graveston", "coaName": "Pregnant Women", "policyKey": "GA_PREGNANT_MEDICAID"}, {"sequence": 27736, "action": "Update Attribute", "element": "classOfAssistance (ClassOfAssistance) [1363]/programFamily", "oldValue": "", "newValue": "Medicaid", "associationEntity": null, "location": "Medicaid Coverage Options : 28", "entityName": "classOfAssistance", "entityType": "ClassOfAssistance", "entityId": 1363, "attributeName": "programFamily", "associationEntityName": null, "associationEntityType": null, "associationEntityId": null, "rulesheetName": "Medicaid Coverage Options", "ruleNumber": "28", "householdId": "77", "familyName": "Graveston", "personId": 273, "personName": "Marti Graveston", "coaName": "Pregnant Women", "policyKey": "GA_PREGNANT_MEDICAID"}, {"sequence": 27737, "action": "Update Attribute", "element": "classOfAssistance (ClassOfAssistance) [1363]/policyKey", "oldValue": "", "newValue": "GA_PREGNANT_MEDICAID", "associationEntity": null, "location": "Medicaid Coverage Options : 28", "entityName": "classOfAssistance", "entityType": "ClassOfAssistance", "entityId": 1363, "attributeName": "policyKey", "associationEntityName": null, "associationEntityType": null, "associationEntityId": null, "rulesheetName": "Medicaid Coverage Options", "ruleNumber": "28", "householdId": "77", "familyName": "Graveston", "personId": 273, "personName": "Marti Graveston", "coaName": "Pregnant Women", "policyKey": "GA_PREGNANT_MEDICAID"}, {"sequence": 27738, "action": "Update Attribute", "element": "classOfAssistance (ClassOfAssistance) [1363]/nonFinancialCriteriaMet", "oldValue": "", "newValue": "true", "associationEntity": null, "location": "Medicaid Coverage Options : 28", "entityName": "classOfAssistance", "entityType": "ClassOfAssistance", "entityId": 1363, "attributeName": "nonFinancialCriteriaMet", "associationEntityName": null, "associationEntityType": null, "associationEntityId": null, "rulesheetName": "Medicaid Coverage Options", "ruleNumber": "28", "householdId": "77", "familyName": "Graveston", "personId": 273, "personName": "Marti Graveston", "coaName": "Pregnant Women", "policyKey": "GA_PREGNANT_MEDICAID"}, {"sequence": 28814, "action": "Add Entity", "element": "classOfAssistance (ClassOfAssistance) [1543]", "oldValue": "", "newValue": "", "associationEntity": null, "location": "Medicaid Coverage Options : 29", "entityName": "classOfAssistance", "entityType": "ClassOfAssistance", "entityId": 1543, "attributeName": null, "associationEntityName": null, "associationEntityType": null, "associationEntityId": null, "rulesheetName": "Medicaid Coverage Options", "ruleNumber": "29", "householdId": "77", "familyName": "Graveston", "personId": 273, "personName": "Marti Graveston", "coaName": "Planning for Healthy Babies", "policyKey": "GA_PLANNING_HEALTHY_BABIES"}, {"sequence": 28815, "action": "Update Attribute", "element": "classOfAssistance (ClassOfAssistance) [1543]/requiresMedicaidIneligibility", "oldValue": "", "newValue": "false", "associationEntity": null, "location": "Medicaid Coverage Options : 29", "entityName": "classOfAssistance", "entityType": "ClassOfAssistance", "entityId": 1543, "attributeName": "requiresMedicaidIneligibility", "associationEntityName": null, "associationEntityType": null, "associationEntityId": null, "rulesheetName": "Medicaid Coverage Options", "ruleNumber": "29", "householdId": "77", "familyName": "Graveston", "personId": 273, "personName": "Marti Graveston", "coaName": "Planning for Healthy Babies", "policyKey": "GA_PLANNING_HEALTHY_BABIES"}, {"sequence": 28816, "action": "Update Attribute", "element": "classOfAssistance (ClassOfAssistance) [1543]/programFamily", "oldValue": "", "newValue": "Medicaid", "associationEntity": null, "location": "Medicaid Coverage Options : 29", "entityName": "classOfAssistance", "entityType": "ClassOfAssistance", "entityId": 1543, "attributeName": "programFamily", "associationEntityName": null, "associationEntityType": null, "associationEntityId": null, "rulesheetName": "Medicaid Coverage Options", "ruleNumber": "29", "householdId": "77", "familyName": "Graveston", "personId": 273, "personName": "Marti Graveston", "coaName": "Planning for Healthy Babies", "policyKey": "GA_PLANNING_HEALTHY_BABIES"}, {"sequence": 28817, "action": "Update Attribute", "element": "classOfAssistance (ClassOfAssistance) [1543]/policyKey", "oldValue": "", "newValue": "GA_PLANNING_HEALTHY_BABIES", "associationEntity": null, "location": "Medicaid Coverage Options : 29", "entityName": "classOfAssistance", "entityType": "ClassOfAssistance", "entityId": 1543, "attributeName": "policyKey", "associationEntityName": null, "associationEntityType": null, "associationEntityId": null, "rulesheetName": "Medicaid Coverage Options", "ruleNumber": "29", "householdId": "77", "familyName": "Graveston", "personId": 273, "personName": "Marti Graveston", "coaName": "Planning for Healthy Babies", "policyKey": "GA_PLANNING_HEALTHY_BABIES"}, {"sequence": 28818, "action": "Update Attribute", "element": "classOfAssistance (ClassOfAssistance) [1543]/nonFinancialCriteriaMet", "oldValue": "", "newValue": "true", "associationEntity": null, "location": "Medicaid Coverage Options : 29", "entityName": "classOfAssistance", "entityType": "ClassOfAssistance", "entityId": 1543, "attributeName": "nonFinancialCriteriaMet", "associationEntityName": null, "associationEntityType": null, "associationEntityId": null, "rulesheetName": "Medicaid Coverage Options", "ruleNumber": "29", "householdId": "77", "familyName": "Graveston", "personId": 273, "personName": "Marti Graveston", "coaName": "Planning for Healthy Babies", "policyKey": "GA_PLANNING_HEALTHY_BABIES"}, {"sequence": 29912, "action": "Add Entity", "element": "classOfAssistance (ClassOfAssistance) [1726]", "oldValue": "", "newValue": "", "associationEntity": null, "location": "Medicaid Coverage Options : 30", "entityName": "classOfAssistance", "entityType": "ClassOfAssistance", "entityId": 1726, "attributeName": null, "associationEntityName": null, "associationEntityType": null, "associationEntityId": null, "rulesheetName": "Medicaid Coverage Options", "ruleNumber": "30", "householdId": "77", "familyName": "Graveston", "personId": 273, "personName": "Marti Graveston", "coaName": "Pathways", "policyKey": "GA_PATHWAYS"}, {"sequence": 29913, "action": "Update Attribute", "element": "classOfAssistance (ClassOfAssistance) [1726]/requiresMedicaidIneligibility", "oldValue": "", "newValue": "false", "associationEntity": null, "location": "Medicaid Coverage Options : 30", "entityName": "classOfAssistance", "entityType": "ClassOfAssistance", "entityId": 1726, "attributeName": "requiresMedicaidIneligibility", "associationEntityName": null, "associationEntityType": null, "associationEntityId": null, "rulesheetName": "Medicaid Coverage Options", "ruleNumber": "30", "householdId": "77", "familyName": "Graveston", "personId": 273, "personName": "Marti Graveston", "coaName": "Pathways", "policyKey": "GA_PATHWAYS"}, {"sequence": 29914, "action": "Update Attribute", "element": "classOfAssistance (ClassOfAssistance) [1726]/programFamily", "oldValue": "", "newValue": "Medicaid", "associationEntity": null, "location": "Medicaid Coverage Options : 30", "entityName": "classOfAssistance", "entityType": "ClassOfAssistance", "entityId": 1726, "attributeName": "programFamily", "associationEntityName": null, "associationEntityType": null, "associationEntityId": null, "rulesheetName": "Medicaid Coverage Options", "ruleNumber": "30", "householdId": "77", "familyName": "Graveston", "personId": 273, "personName": "Marti Graveston", "coaName": "Pathways", "policyKey": "GA_PATHWAYS"}, {"sequence": 29915, "action": "Update Attribute", "element": "classOfAssistance (ClassOfAssistance) [1726]/policyKey", "oldValue": "", "newValue": "GA_PATHWAYS", "associationEntity": null, "location": "Medicaid Coverage Options : 30", "entityName": "classOfAssistance", "entityType": "ClassOfAssistance", "entityId": 1726, "attributeName": "policyKey", "associationEntityName": null, "associationEntityType": null, "associationEntityId": null, "rulesheetName": "Medicaid Coverage Options", "ruleNumber": "30", "householdId": "77", "familyName": "Graveston", "personId": 273, "personName": "Marti Graveston", "coaName": "Pathways", "policyKey": "GA_PATHWAYS"}, {"sequence": 29916, "action": "Update Attribute", "element": "classOfAssistance (ClassOfAssistance) [1726]/nonFinancialCriteriaMet", "oldValue": "", "newValue": "true", "associationEntity": null, "location": "Medicaid Coverage Options : 30", "entityName": "classOfAssistance", "entityType": "ClassOfAssistance", "entityId": 1726, "attributeName": "nonFinancialCriteriaMet", "associationEntityName": null, "associationEntityType": null, "associationEntityId": null, "rulesheetName": "Medicaid Coverage Options", "ruleNumber": "30", "householdId": "77", "familyName": "Graveston", "personId": 273, "personName": "Marti Graveston", "coaName": "Pathways", "policyKey": "GA_PATHWAYS"}, {"sequence": 30908, "action": "Add Entity", "element": "classOfAssistance (ClassOfAssistance) [1892]", "oldValue": "", "newValue": "", "associationEntity": null, "location": "Medicaid Coverage Options : 31", "entityName": "classOfAssistance", "entityType": "ClassOfAssistance", "entityId": 1892, "attributeName": null, "associationEntityName": null, "associationEntityType": null, "associationEntityId": null, "rulesheetName": "Medicaid Coverage Options", "ruleNumber": "31", "householdId": "77", "familyName": "Graveston", "personId": 273, "personName": "Marti Graveston", "coaName": "Family Medicaid Medically Needy", "policyKey": "GA_FAMILY_MED_NEEDY"}, {"sequence": 30909, "action": "Update Attribute", "element": "classOfAssistance (ClassOfAssistance) [1892]/requiresMedicaidIneligibility", "oldValue": "", "newValue": "false", "associationEntity": null, "location": "Medicaid Coverage Options : 31", "entityName": "classOfAssistance", "entityType": "ClassOfAssistance", "entityId": 1892, "attributeName": "requiresMedicaidIneligibility", "associationEntityName": null, "associationEntityType": null, "associationEntityId": null, "rulesheetName": "Medicaid Coverage Options", "ruleNumber": "31", "householdId": "77", "familyName": "Graveston", "personId": 273, "personName": "Marti Graveston", "coaName": "Family Medicaid Medically Needy", "policyKey": "GA_FAMILY_MED_NEEDY"}, {"sequence": 30910, "action": "Update Attribute", "element": "classOfAssistance (ClassOfAssistance) [1892]/programFamily", "oldValue": "", "newValue": "Medicaid", "associationEntity": null, "location": "Medicaid Coverage Options : 31", "entityName": "classOfAssistance", "entityType": "ClassOfAssistance", "entityId": 1892, "attributeName": "programFamily", "associationEntityName": null, "associationEntityType": null, "associationEntityId": null, "rulesheetName": "Medicaid Coverage Options", "ruleNumber": "31", "householdId": "77", "familyName": "Graveston", "personId": 273, "personName": "Marti Graveston", "coaName": "Family Medicaid Medically Needy", "policyKey": "GA_FAMILY_MED_NEEDY"}, {"sequence": 30911, "action": "Update Attribute", "element": "classOfAssistance (ClassOfAssistance) [1892]/policyKey", "oldValue": "", "newValue": "GA_FAMILY_MED_NEEDY", "associationEntity": null, "location": "Medicaid Coverage Options : 31", "entityName": "classOfAssistance", "entityType": "ClassOfAssistance", "entityId": 1892, "attributeName": "policyKey", "associationEntityName": null, "associationEntityType": null, "associationEntityId": null, "rulesheetName": "Medicaid Coverage Options", "ruleNumber": "31", "householdId": "77", "familyName": "Graveston", "personId": 273, "personName": "Marti Graveston", "coaName": "Family Medicaid Medically Needy", "policyKey": "GA_FAMILY_MED_NEEDY"}, {"sequence": 30912, "action": "Update Attribute", "element": "classOfAssistance (ClassOfAssistance) [1892]/nonFinancialCriteriaMet", "oldValue": "", "newValue": "true", "associationEntity": null, "location": "Medicaid Coverage Options : 31", "entityName": "classOfAssistance", "entityType": "ClassOfAssistance", "entityId": 1892, "attributeName": "nonFinancialCriteriaMet", "associationEntityName": null, "associationEntityType": null, "associationEntityId": null, "rulesheetName": "Medicaid Coverage Options", "ruleNumber": "31", "householdId": "77", "familyName": "Graveston", "personId": 273, "personName": "Marti Graveston", "coaName": "Family Medicaid Medically Needy", "policyKey": "GA_FAMILY_MED_NEEDY"}, {"sequence": 33140, "action": "Add Entity", "element": "classOfAssistance (ClassOfAssistance) [2264]", "oldValue": "", "newValue": "", "associationEntity": null, "location": "Medicaid Coverage Options : 33", "entityName": "classOfAssistance", "entityType": "ClassOfAssistance", "entityId": 2264, "attributeName": null, "associationEntityName": null, "associationEntityType": null, "associationEntityId": null, "rulesheetName": "Medicaid Coverage Options", "ruleNumber": "33", "householdId": "77", "familyName": "Graveston", "personId": 273, "personName": "Marti Graveston", "coaName": "Women's Health Medicaid", "policyKey": "GA_WOMENS_HEALTH"}, {"sequence": 33141, "action": "Update Attribute", "element": "classOfAssistance (ClassOfAssistance) [2264]/requiresMedicaidIneligibility", "oldValue": "", "newValue": "false", "associationEntity": null, "location": "Medicaid Coverage Options : 33", "entityName": "classOfAssistance", "entityType": "ClassOfAssistance", "entityId": 2264, "attributeName": "requiresMedicaidIneligibility", "associationEntityName": null, "associationEntityType": null, "associationEntityId": null, "rulesheetName": "Medicaid Coverage Options", "ruleNumber": "33", "householdId": "77", "familyName": "Graveston", "personId": 273, "personName": "Marti Graveston", "coaName": "Women's Health Medicaid", "policyKey": "GA_WOMENS_HEALTH"}, {"sequence": 33142, "action": "Update Attribute", "element": "classOfAssistance (ClassOfAssistance) [2264]/programFamily", "oldValue": "", "newValue": "Medicaid", "associationEntity": null, "location": "Medicaid Coverage Options : 33", "entityName": "classOfAssistance", "entityType": "ClassOfAssistance", "entityId": 2264, "attributeName": "programFamily", "associationEntityName": null, "associationEntityType": null, "associationEntityId": null, "rulesheetName": "Medicaid Coverage Options", "ruleNumber": "33", "householdId": "77", "familyName": "Graveston", "personId": 273, "personName": "Marti Graveston", "coaName": "Women's Health Medicaid", "policyKey": "GA_WOMENS_HEALTH"}, {"sequence": 33143, "action": "Update Attribute", "element": "classOfAssistance (ClassOfAssistance) [2264]/policyKey", "oldValue": "", "newValue": "GA_WOMENS_HEALTH", "associationEntity": null, "location": "Medicaid Coverage Options : 33", "entityName": "classOfAssistance", "entityType": "ClassOfAssistance", "entityId": 2264, "attributeName": "policyKey", "associationEntityName": null, "associationEntityType": null, "associationEntityId": null, "rulesheetName": "Medicaid Coverage Options", "ruleNumber": "33", "householdId": "77", "familyName": "Graveston", "personId": 273, "personName": "Marti Graveston", "coaName": "Women's Health Medicaid", "policyKey": "GA_WOMENS_HEALTH"}, {"sequence": 33144, "action": "Update Attribute", "element": "classOfAssistance (ClassOfAssistance) [2264]/nonFinancialCriteriaMet", "oldValue": "", "newValue": "true", "associationEntity": null, "location": "Medicaid Coverage Options : 33", "entityName": "classOfAssistance", "entityType": "ClassOfAssistance", "entityId": 2264, "attributeName": "nonFinancialCriteriaMet", "associationEntityName": null, "associationEntityType": null, "associationEntityId": null, "rulesheetName": "Medicaid Coverage Options", "ruleNumber": "33", "householdId": "77", "familyName": "Graveston", "personId": 273, "personName": "Marti Graveston", "coaName": "Women's Health Medicaid", "policyKey": "GA_WOMENS_HEALTH"}, {"sequence": 34256, "action": "Add Entity", "element": "classOfAssistance (ClassOfAssistance) [2450]", "oldValue": "", "newValue": "", "associationEntity": null, "location": "Medicaid Coverage Options : 34", "entityName": "classOfAssistance", "entityType": "ClassOfAssistance", "entityId": 2450, "attributeName": null, "associationEntityName": null, "associationEntityType": null, "associationEntityId": null, "rulesheetName": "Medicaid Coverage Options", "ruleNumber": "34", "householdId": "77", "familyName": "Graveston", "personId": 273, "personName": "Marti Graveston", "coaName": "Supplemental Security Income (SSI) Medicaid", "policyKey": "GA_SSI_MEDICAID"}, {"sequence": 34257, "action": "Update Attribute", "element": "classOfAssistance (ClassOfAssistance) [2450]/requiresMedicaidIneligibility", "oldValue": "", "newValue": "false", "associationEntity": null, "location": "Medicaid Coverage Options : 34", "entityName": "classOfAssistance", "entityType": "ClassOfAssistance", "entityId": 2450, "attributeName": "requiresMedicaidIneligibility", "associationEntityName": null, "associationEntityType": null, "associationEntityId": null, "rulesheetName": "Medicaid Coverage Options", "ruleNumber": "34", "householdId": "77", "familyName": "Graveston", "personId": 273, "personName": "Marti Graveston", "coaName": "Supplemental Security Income (SSI) Medicaid", "policyKey": "GA_SSI_MEDICAID"}, {"sequence": 34258, "action": "Update Attribute", "element": "classOfAssistance (ClassOfAssistance) [2450]/programFamily", "oldValue": "", "newValue": "Medicaid", "associationEntity": null, "location": "Medicaid Coverage Options : 34", "entityName": "classOfAssistance", "entityType": "ClassOfAssistance", "entityId": 2450, "attributeName": "programFamily", "associationEntityName": null, "associationEntityType": null, "associationEntityId": null, "rulesheetName": "Medicaid Coverage Options", "ruleNumber": "34", "householdId": "77", "familyName": "Graveston", "personId": 273, "personName": "Marti Graveston", "coaName": "Supplemental Security Income (SSI) Medicaid", "policyKey": "GA_SSI_MEDICAID"}, {"sequence": 34259, "action": "Update Attribute", "element": "classOfAssistance (ClassOfAssistance) [2450]/policyKey", "oldValue": "", "newValue": "GA_SSI_MEDICAID", "associationEntity": null, "location": "Medicaid Coverage Options : 34", "entityName": "classOfAssistance", "entityType": "ClassOfAssistance", "entityId": 2450, "attributeName": "policyKey", "associationEntityName": null, "associationEntityType": null, "associationEntityId": null, "rulesheetName": "Medicaid Coverage Options", "ruleNumber": "34", "householdId": "77", "familyName": "Graveston", "personId": 273, "personName": "Marti Graveston", "coaName": "Supplemental Security Income (SSI) Medicaid", "policyKey": "GA_SSI_MEDICAID"}, {"sequence": 34260, "action": "Update Attribute", "element": "classOfAssistance (ClassOfAssistance) [2450]/nonFinancialCriteriaMet", "oldValue": "", "newValue": "true", "associationEntity": null, "location": "Medicaid Coverage Options : 34", "entityName": "classOfAssistance", "entityType": "ClassOfAssistance", "entityId": 2450, "attributeName": "nonFinancialCriteriaMet", "associationEntityName": null, "associationEntityType": null, "associationEntityId": null, "rulesheetName": "Medicaid Coverage Options", "ruleNumber": "34", "householdId": "77", "familyName": "Graveston", "personId": 273, "personName": "Marti Graveston", "coaName": "Supplemental Security Income (SSI) Medicaid", "policyKey": "GA_SSI_MEDICAID"}, {"sequence": 35156, "action": "Add Entity", "element": "classOfAssistance (ClassOfAssistance) [2600]", "oldValue": "", "newValue": "", "associationEntity": null, "location": "Medicaid Coverage Options : 35", "entityName": "classOfAssistance", "entityType": "ClassOfAssistance", "entityId": 2600, "attributeName": null, "associationEntityName": null, "associationEntityType": null, "associationEntityId": null, "rulesheetName": "Medicaid Coverage Options", "ruleNumber": "35", "householdId": "77", "familyName": "Graveston", "personId": 273, "personName": "Marti Graveston", "coaName": "Pickle", "policyKey": "GA_PICKLE"}, {"sequence": 35157, "action": "Update Attribute", "element": "classOfAssistance (ClassOfAssistance) [2600]/requiresMedicaidIneligibility", "oldValue": "", "newValue": "false", "associationEntity": null, "location": "Medicaid Coverage Options : 35", "entityName": "classOfAssistance", "entityType": "ClassOfAssistance", "entityId": 2600, "attributeName": "requiresMedicaidIneligibility", "associationEntityName": null, "associationEntityType": null, "associationEntityId": null, "rulesheetName": "Medicaid Coverage Options", "ruleNumber": "35", "householdId": "77", "familyName": "Graveston", "personId": 273, "personName": "Marti Graveston", "coaName": "Pickle", "policyKey": "GA_PICKLE"}, {"sequence": 35158, "action": "Update Attribute", "element": "classOfAssistance (ClassOfAssistance) [2600]/programFamily", "oldValue": "", "newValue": "Medicaid", "associationEntity": null, "location": "Medicaid Coverage Options : 35", "entityName": "classOfAssistance", "entityType": "ClassOfAssistance", "entityId": 2600, "attributeName": "programFamily", "associationEntityName": null, "associationEntityType": null, "associationEntityId": null, "rulesheetName": "Medicaid Coverage Options", "ruleNumber": "35", "householdId": "77", "familyName": "Graveston", "personId": 273, "personName": "Marti Graveston", "coaName": "Pickle", "policyKey": "GA_PICKLE"}, {"sequence": 35159, "action": "Update Attribute", "element": "classOfAssistance (ClassOfAssistance) [2600]/policyKey", "oldValue": "", "newValue": "GA_PICKLE", "associationEntity": null, "location": "Medicaid Coverage Options : 35", "entityName": "classOfAssistance", "entityType": "ClassOfAssistance", "entityId": 2600, "attributeName": "policyKey", "associationEntityName": null, "associationEntityType": null, "associationEntityId": null, "rulesheetName": "Medicaid Coverage Options", "ruleNumber": "35", "householdId": "77", "familyName": "Graveston", "personId": 273, "personName": "Marti Graveston", "coaName": "Pickle", "policyKey": "GA_PICKLE"}, {"sequence": 35160, "action": "Update Attribute", "element": "classOfAssistance (ClassOfAssistance) [2600]/nonFinancialCriteriaMet", "oldValue": "", "newValue": "true", "associationEntity": null, "location": "Medicaid Coverage Options : 35", "entityName": "classOfAssistance", "entityType": "ClassOfAssistance", "entityId": 2600, "attributeName": "nonFinancialCriteriaMet", "associationEntityName": null, "associationEntityType": null, "associationEntityId": null, "rulesheetName": "Medicaid Coverage Options", "ruleNumber": "35", "householdId": "77", "familyName": "Graveston", "personId": 273, "personName": "Marti Graveston", "coaName": "Pickle", "policyKey": "GA_PICKLE"}, {"sequence": 35724, "action": "Update Attribute", "element": "classOfAssistance (ClassOfAssistance) [29]/name", "oldValue": "", "newValue": "Supplemental Security Income (SSI) Medicaid", "associationEntity": null, "location": "COA Detail : 7", "entityName": "classOfAssistance", "entityType": "ClassOfAssistance", "entityId": 29, "attributeName": "name", "associationEntityName": null, "associationEntityType": null, "associationEntityId": null, "rulesheetName": "COA Detail", "ruleNumber": "7", "householdId": "77", "familyName": "Graveston", "personId": 273, "personName": "Marti Graveston", "coaName": "Supplemental Security Income (SSI) Medicaid", "policyKey": "GA_SSI_MEDICAID"}, {"sequence": 35802, "action": "Update Attribute", "element": "classOfAssistance (ClassOfAssistance) [2450]/name", "oldValue": "", "newValue": "Supplemental Security Income (SSI) Medicaid", "associationEntity": null, "location": "COA Detail : 7", "entityName": "classOfAssistance", "entityType": "ClassOfAssistance", "entityId": 2450, "attributeName": "name", "associationEntityName": null, "associationEntityType": null, "associationEntityId": null, "rulesheetName": "COA Detail", "ruleNumber": "7", "householdId": "77", "familyName": "Graveston", "personId": 273, "personName": "Marti Graveston", "coaName": "Supplemental Security Income (SSI) Medicaid", "policyKey": "GA_SSI_MEDICAID"}, {"sequence": 35981, "action": "Update Attribute", "element": "classOfAssistance (ClassOfAssistance) [179]/name", "oldValue": "", "newValue": "Pickle", "associationEntity": null, "location": "COA Detail : 8", "entityName": "classOfAssistance", "entityType": "ClassOfAssistance", "entityId": 179, "attributeName": "name", "associationEntityName": null, "associationEntityType": null, "associationEntityId": null, "rulesheetName": "COA Detail", "ruleNumber": "8", "householdId": "77", "familyName": "Graveston", "personId": 273, "personName": "Marti Graveston", "coaName": "Pickle", "policyKey": "GA_PICKLE"}, {"sequence": 36022, "action": "Update Attribute", "element": "classOfAssistance (ClassOfAssistance) [2600]/name", "oldValue": "", "newValue": "Pickle", "associationEntity": null, "location": "COA Detail : 8", "entityName": "classOfAssistance", "entityType": "ClassOfAssistance", "entityId": 2600, "attributeName": "name", "associationEntityName": null, "associationEntityType": null, "associationEntityId": null, "rulesheetName": "COA Detail", "ruleNumber": "8", "householdId": "77", "familyName": "Graveston", "personId": 273, "personName": "Marti Graveston", "coaName": "Pickle", "policyKey": "GA_PICKLE"}, {"sequence": 36180, "action": "Update Attribute", "element": "classOfAssistance (ClassOfAssistance) [265]/name", "oldValue": "", "newValue": "Protected Medicaid 1972", "associationEntity": null, "location": "COA Detail : 11", "entityName": "classOfAssistance", "entityType": "ClassOfAssistance", "entityId": 265, "attributeName": "name", "associationEntityName": null, "associationEntityType": null, "associationEntityId": null, "rulesheetName": "COA Detail", "ruleNumber": "11", "householdId": "77", "familyName": "Graveston", "personId": 273, "personName": "Marti Graveston", "coaName": "Protected Medicaid 1972", "policyKey": "GA_PROTECTED_MEDICAID_1972"}, {"sequence": 36220, "action": "Update Attribute", "element": "classOfAssistance (ClassOfAssistance) [463]/name", "oldValue": "", "newValue": "ABD Medically Needy", "associationEntity": null, "location": "COA Detail : 12", "entityName": "classOfAssistance", "entityType": "ClassOfAssistance", "entityId": 463, "attributeName": "name", "associationEntityName": null, "associationEntityType": null, "associationEntityId": null, "rulesheetName": "COA Detail", "ruleNumber": "12", "householdId": "77", "familyName": "Graveston", "personId": 273, "personName": "Marti Graveston", "coaName": "ABD Medically Needy", "policyKey": "GA_ABD_MED_NEEDY"}, {"sequence": 36863, "action": "Update Attribute", "element": "classOfAssistance (ClassOfAssistance) [1363]/name", "oldValue": "", "newValue": "Pregnant Women", "associationEntity": null, "location": "COA Detail : 19", "entityName": "classOfAssistance", "entityType": "ClassOfAssistance", "entityId": 1363, "attributeName": "name", "associationEntityName": null, "associationEntityType": null, "associationEntityId": null, "rulesheetName": "COA Detail", "ruleNumber": "19", "householdId": "77", "familyName": "Graveston", "personId": 273, "personName": "Marti Graveston", "coaName": "Pregnant Women", "policyKey": "GA_PREGNANT_MEDICAID"}, {"sequence": 37324, "action": "Update Attribute", "element": "classOfAssistance (ClassOfAssistance) [2264]/name", "oldValue": "", "newValue": "Women's Health Medicaid", "associationEntity": null, "location": "COA Detail : 25", "entityName": "classOfAssistance", "entityType": "ClassOfAssistance", "entityId": 2264, "attributeName": "name", "associationEntityName": null, "associationEntityType": null, "associationEntityId": null, "rulesheetName": "COA Detail", "ruleNumber": "25", "householdId": "77", "familyName": "Graveston", "personId": 273, "personName": "Marti Graveston", "coaName": "Women's Health Medicaid", "policyKey": "GA_WOMENS_HEALTH"}, {"sequence": 37524, "action": "Update Attribute", "element": "classOfAssistance (ClassOfAssistance) [1726]/name", "oldValue": "", "newValue": "Pathways", "associationEntity": null, "location": "COA Detail : 26", "entityName": "classOfAssistance", "entityType": "ClassOfAssistance", "entityId": 1726, "attributeName": "name", "associationEntityName": null, "associationEntityType": null, "associationEntityId": null, "rulesheetName": "COA Detail", "ruleNumber": "26", "householdId": "77", "familyName": "Graveston", "personId": 273, "personName": "Marti Graveston", "coaName": "Pathways", "policyKey": "GA_PATHWAYS"}, {"sequence": 37820, "action": "Update Attribute", "element": "classOfAssistance (ClassOfAssistance) [1543]/name", "oldValue": "", "newValue": "Planning for Healthy Babies", "associationEntity": null, "location": "COA Detail : 27", "entityName": "classOfAssistance", "entityType": "ClassOfAssistance", "entityId": 1543, "attributeName": "name", "associationEntityName": null, "associationEntityType": null, "associationEntityId": null, "rulesheetName": "COA Detail", "ruleNumber": "27", "householdId": "77", "familyName": "Graveston", "personId": 273, "personName": "Marti Graveston", "coaName": "Planning for Healthy Babies", "policyKey": "GA_PLANNING_HEALTHY_BABIES"}, {"sequence": 38078, "action": "Update Attribute", "element": "classOfAssistance (ClassOfAssistance) [1892]/name", "oldValue": "", "newValue": "Family Medicaid Medically Needy", "associationEntity": null, "location": "COA Detail : 28", "entityName": "classOfAssistance", "entityType": "ClassOfAssistance", "entityId": 1892, "attributeName": "name", "associationEntityName": null, "associationEntityType": null, "associationEntityId": null, "rulesheetName": "COA Detail", "ruleNumber": "28", "householdId": "77", "familyName": "Graveston", "personId": 273, "personName": "Marti Graveston", "coaName": "Family Medicaid Medically Needy", "policyKey": "GA_FAMILY_MED_NEEDY"}, {"sequence": 38527, "action": "Update Attribute", "element": "classOfAssistance (ClassOfAssistance) [2450]/incomeThreshold", "oldValue": "", "newValue": "16432.5", "associationEntity": null, "location": "Aged", "entityName": "classOfAssistance", "entityType": "ClassOfAssistance", "entityId": 2450, "attributeName": "incomeThreshold", "associationEntityName": null, "associationEntityType": null, "associationEntityId": null, "rulesheetName": null, "ruleNumber": null, "householdId": "77", "familyName": "Graveston", "personId": 273, "personName": "Marti Graveston", "coaName": "Supplemental Security Income (SSI) Medicaid", "policyKey": "GA_SSI_MEDICAID"}, {"sequence": 38561, "action": "Update Attribute", "element": "classOfAssistance (ClassOfAssistance) [29]/incomeThreshold", "oldValue": "", "newValue": "16432.5", "associationEntity": null, "location": "Aged", "entityName": "classOfAssistance", "entityType": "ClassOfAssistance", "entityId": 29, "attributeName": "incomeThreshold", "associationEntityName": null, "associationEntityType": null, "associationEntityId": null, "rulesheetName": null, "ruleNumber": null, "householdId": "77", "familyName": "Graveston", "personId": 273, "personName": "Marti Graveston", "coaName": "Supplemental Security Income (SSI) Medicaid", "policyKey": "GA_SSI_MEDICAID"}, {"sequence": 38671, "action": "Update Attribute", "element": "classOfAssistance (ClassOfAssistance) [2600]/incomeThreshold", "oldValue": "", "newValue": "16432.5", "associationEntity": null, "location": "Aged", "entityName": "classOfAssistance", "entityType": "ClassOfAssistance", "entityId": 2600, "attributeName": "incomeThreshold", "associationEntityName": null, "associationEntityType": null, "associationEntityId": null, "rulesheetName": null, "ruleNumber": null, "householdId": "77", "familyName": "Graveston", "personId": 273, "personName": "Marti Graveston", "coaName": "Pickle", "policyKey": "GA_PICKLE"}, {"sequence": 38736, "action": "Update Attribute", "element": "classOfAssistance (ClassOfAssistance) [179]/incomeThreshold", "oldValue": "", "newValue": "16432.5", "associationEntity": null, "location": "Aged", "entityName": "classOfAssistance", "entityType": "ClassOfAssistance", "entityId": 179, "attributeName": "incomeThreshold", "associationEntityName": null, "associationEntityType": null, "associationEntityId": null, "rulesheetName": null, "ruleNumber": null, "householdId": "77", "familyName": "Graveston", "personId": 273, "personName": "Marti Graveston", "coaName": "Pickle", "policyKey": "GA_PICKLE"}, {"sequence": 38829, "action": "Update Attribute", "element": "classOfAssistance (ClassOfAssistance) [265]/incomeThreshold", "oldValue": "", "newValue": "995.4", "associationEntity": null, "location": "Aged", "entityName": "classOfAssistance", "entityType": "ClassOfAssistance", "entityId": 265, "attributeName": "incomeThreshold", "associationEntityName": null, "associationEntityType": null, "associationEntityId": null, "rulesheetName": null, "ruleNumber": null, "householdId": "77", "familyName": "Graveston", "personId": 273, "personName": "Marti Graveston", "coaName": "Protected Medicaid 1972", "policyKey": "GA_PROTECTED_MEDICAID_1972"}, {"sequence": 38830, "action": "Update Attribute", "element": "classOfAssistance (ClassOfAssistance) [265]/resourceThreshold", "oldValue": "", "newValue": "1500", "associationEntity": null, "location": "Aged", "entityName": "classOfAssistance", "entityType": "ClassOfAssistance", "entityId": 265, "attributeName": "resourceThreshold", "associationEntityName": null, "associationEntityType": null, "associationEntityId": null, "rulesheetName": null, "ruleNumber": null, "householdId": "77", "familyName": "Graveston", "personId": 273, "personName": "Marti Graveston", "coaName": "Protected Medicaid 1972", "policyKey": "GA_PROTECTED_MEDICAID_1972"}, {"sequence": 40758, "action": "Update Attribute", "element": "classOfAssistance (ClassOfAssistance) [1363]/incomeThreshold", "oldValue": "", "newValue": "36151.5", "associationEntity": null, "location": "Family Medicaid (MAGI) Groups : 3", "entityName": "classOfAssistance", "entityType": "ClassOfAssistance", "entityId": 1363, "attributeName": "incomeThreshold", "associationEntityName": null, "associationEntityType": null, "associationEntityId": null, "rulesheetName": "Family Medicaid (MAGI) Groups", "ruleNumber": "3", "householdId": "77", "familyName": "Graveston", "personId": 273, "personName": "Marti Graveston", "coaName": "Pregnant Women", "policyKey": "GA_PREGNANT_MEDICAID"}, {"sequence": 41058, "action": "Update Attribute", "element": "classOfAssistance (ClassOfAssistance) [1543]/incomeThreshold", "oldValue": "", "newValue": "32865", "associationEntity": null, "location": "Family Medicaid (MAGI) Groups : 4", "entityName": "classOfAssistance", "entityType": "ClassOfAssistance", "entityId": 1543, "attributeName": "incomeThreshold", "associationEntityName": null, "associationEntityType": null, "associationEntityId": null, "rulesheetName": "Family Medicaid (MAGI) Groups", "ruleNumber": "4", "householdId": "77", "familyName": "Graveston", "personId": 273, "personName": "Marti Graveston", "coaName": "Planning for Healthy Babies", "policyKey": "GA_PLANNING_HEALTHY_BABIES"}, {"sequence": 42168, "action": "Update Attribute", "element": "classOfAssistance (ClassOfAssistance) [1726]/incomeThreshold", "oldValue": "", "newValue": "16432.5", "associationEntity": null, "location": "Family Medicaid (MAGI) Groups : 5", "entityName": "classOfAssistance", "entityType": "ClassOfAssistance", "entityId": 1726, "attributeName": "incomeThreshold", "associationEntityName": null, "associationEntityType": null, "associationEntityId": null, "rulesheetName": "Family Medicaid (MAGI) Groups", "ruleNumber": "5", "householdId": "77", "familyName": "Graveston", "personId": 273, "personName": "Marti Graveston", "coaName": "Pathways", "policyKey": "GA_PATHWAYS"}, {"sequence": 42169, "action": "Update Attribute", "element": "classOfAssistance (ClassOfAssistance) [1726]/requiresQualifyingActivities", "oldValue": "", "newValue": "true", "associationEntity": null, "location": "Family Medicaid (MAGI) Groups : 5", "entityName": "classOfAssistance", "entityType": "ClassOfAssistance", "entityId": 1726, "attributeName": "requiresQualifyingActivities", "associationEntityName": null, "associationEntityType": null, "associationEntityId": null, "rulesheetName": "Family Medicaid (MAGI) Groups", "ruleNumber": "5", "householdId": "77", "familyName": "Graveston", "personId": 273, "personName": "Marti Graveston", "coaName": "Pathways", "policyKey": "GA_PATHWAYS"}, {"sequence": 43917, "action": "Update Attribute", "element": "classOfAssistance (ClassOfAssistance) [2264]/incomeThreshold", "oldValue": "", "newValue": "32865", "associationEntity": null, "location": "Family Medicaid (MAGI) Groups : 7", "entityName": "classOfAssistance", "entityType": "ClassOfAssistance", "entityId": 2264, "attributeName": "incomeThreshold", "associationEntityName": null, "associationEntityType": null, "associationEntityId": null, "rulesheetName": "Family Medicaid (MAGI) Groups", "ruleNumber": "7", "householdId": "77", "familyName": "Graveston", "personId": 273, "personName": "Marti Graveston", "coaName": "Women's Health Medicaid", "policyKey": "GA_WOMENS_HEALTH"}, {"sequence": 44994, "action": "Update Attribute", "element": "classOfAssistance (ClassOfAssistance) [29]/group", "oldValue": "", "newValue": "SSI and SSI-Derived", "associationEntity": null, "location": "COA Ordering : 7", "entityName": "classOfAssistance", "entityType": "ClassOfAssistance", "entityId": 29, "attributeName": "group", "associationEntityName": null, "associationEntityType": null, "associationEntityId": null, "rulesheetName": "COA Ordering", "ruleNumber": "7", "householdId": "77", "familyName": "Graveston", "personId": 273, "personName": "Marti Graveston", "coaName": "Supplemental Security Income (SSI) Medicaid", "policyKey": "GA_SSI_MEDICAID"}, {"sequence": 44995, "action": "Update Attribute", "element": "classOfAssistance (ClassOfAssistance) [29]/groupRank", "oldValue": "", "newValue": "20", "associationEntity": null, "location": "COA Ordering : 7", "entityName": "classOfAssistance", "entityType": "ClassOfAssistance", "entityId": 29, "attributeName": "groupRank", "associationEntityName": null, "associationEntityType": null, "associationEntityId": null, "rulesheetName": "COA Ordering", "ruleNumber": "7", "householdId": "77", "familyName": "Graveston", "personId": 273, "personName": "Marti Graveston", "coaName": "Supplemental Security Income (SSI) Medicaid", "policyKey": "GA_SSI_MEDICAID"}, {"sequence": 44996, "action": "Update Attribute", "element": "classOfAssistance (ClassOfAssistance) [29]/priorityForGroup", "oldValue": "", "newValue": "1", "associationEntity": null, "location": "COA Ordering : 7", "entityName": "classOfAssistance", "entityType": "ClassOfAssistance", "entityId": 29, "attributeName": "priorityForGroup", "associationEntityName": null, "associationEntityType": null, "associationEntityId": null, "rulesheetName": "COA Ordering", "ruleNumber": "7", "householdId": "77", "familyName": "Graveston", "personId": 273, "personName": "Marti Graveston", "coaName": "Supplemental Security Income (SSI) Medicaid", "policyKey": "GA_SSI_MEDICAID"}, {"sequence": 45228, "action": "Update Attribute", "element": "classOfAssistance (ClassOfAssistance) [2450]/group", "oldValue": "", "newValue": "SSI and SSI-Derived", "associationEntity": null, "location": "COA Ordering : 7", "entityName": "classOfAssistance", "entityType": "ClassOfAssistance", "entityId": 2450, "attributeName": "group", "associationEntityName": null, "associationEntityType": null, "associationEntityId": null, "rulesheetName": "COA Ordering", "ruleNumber": "7", "householdId": "77", "familyName": "Graveston", "personId": 273, "personName": "Marti Graveston", "coaName": "Supplemental Security Income (SSI) Medicaid", "policyKey": "GA_SSI_MEDICAID"}, {"sequence": 45229, "action": "Update Attribute", "element": "classOfAssistance (ClassOfAssistance) [2450]/groupRank", "oldValue": "", "newValue": "20", "associationEntity": null, "location": "COA Ordering : 7", "entityName": "classOfAssistance", "entityType": "ClassOfAssistance", "entityId": 2450, "attributeName": "groupRank", "associationEntityName": null, "associationEntityType": null, "associationEntityId": null, "rulesheetName": "COA Ordering", "ruleNumber": "7", "householdId": "77", "familyName": "Graveston", "personId": 273, "personName": "Marti Graveston", "coaName": "Supplemental Security Income (SSI) Medicaid", "policyKey": "GA_SSI_MEDICAID"}, {"sequence": 45230, "action": "Update Attribute", "element": "classOfAssistance (ClassOfAssistance) [2450]/priorityForGroup", "oldValue": "", "newValue": "1", "associationEntity": null, "location": "COA Ordering : 7", "entityName": "classOfAssistance", "entityType": "ClassOfAssistance", "entityId": 2450, "attributeName": "priorityForGroup", "associationEntityName": null, "associationEntityType": null, "associationEntityId": null, "rulesheetName": "COA Ordering", "ruleNumber": "7", "householdId": "77", "familyName": "Graveston", "personId": 273, "personName": "Marti Graveston", "coaName": "Supplemental Security Income (SSI) Medicaid", "policyKey": "GA_SSI_MEDICAID"}, {"sequence": 45765, "action": "Update Attribute", "element": "classOfAssistance (ClassOfAssistance) [179]/group", "oldValue": "", "newValue": "SSI and SSI-Derived", "associationEntity": null, "location": "COA Ordering : 8", "entityName": "classOfAssistance", "entityType": "ClassOfAssistance", "entityId": 179, "attributeName": "group", "associationEntityName": null, "associationEntityType": null, "associationEntityId": null, "rulesheetName": "COA Ordering", "ruleNumber": "8", "householdId": "77", "familyName": "Graveston", "personId": 273, "personName": "Marti Graveston", "coaName": "Pickle", "policyKey": "GA_PICKLE"}, {"sequence": 45766, "action": "Update Attribute", "element": "classOfAssistance (ClassOfAssistance) [179]/groupRank", "oldValue": "", "newValue": "20", "associationEntity": null, "location": "COA Ordering : 8", "entityName": "classOfAssistance", "entityType": "ClassOfAssistance", "entityId": 179, "attributeName": "groupRank", "associationEntityName": null, "associationEntityType": null, "associationEntityId": null, "rulesheetName": "COA Ordering", "ruleNumber": "8", "householdId": "77", "familyName": "Graveston", "personId": 273, "personName": "Marti Graveston", "coaName": "Pickle", "policyKey": "GA_PICKLE"}, {"sequence": 45767, "action": "Update Attribute", "element": "classOfAssistance (ClassOfAssistance) [179]/priorityForGroup", "oldValue": "", "newValue": "2", "associationEntity": null, "location": "COA Ordering : 8", "entityName": "classOfAssistance", "entityType": "ClassOfAssistance", "entityId": 179, "attributeName": "priorityForGroup", "associationEntityName": null, "associationEntityType": null, "associationEntityId": null, "rulesheetName": "COA Ordering", "ruleNumber": "8", "householdId": "77", "familyName": "Graveston", "personId": 273, "personName": "Marti Graveston", "coaName": "Pickle", "policyKey": "GA_PICKLE"}, {"sequence": 45888, "action": "Update Attribute", "element": "classOfAssistance (ClassOfAssistance) [2600]/group", "oldValue": "", "newValue": "SSI and SSI-Derived", "associationEntity": null, "location": "COA Ordering : 8", "entityName": "classOfAssistance", "entityType": "ClassOfAssistance", "entityId": 2600, "attributeName": "group", "associationEntityName": null, "associationEntityType": null, "associationEntityId": null, "rulesheetName": "COA Ordering", "ruleNumber": "8", "householdId": "77", "familyName": "Graveston", "personId": 273, "personName": "Marti Graveston", "coaName": "Pickle", "policyKey": "GA_PICKLE"}, {"sequence": 45889, "action": "Update Attribute", "element": "classOfAssistance (ClassOfAssistance) [2600]/groupRank", "oldValue": "", "newValue": "20", "associationEntity": null, "location": "COA Ordering : 8", "entityName": "classOfAssistance", "entityType": "ClassOfAssistance", "entityId": 2600, "attributeName": "groupRank", "associationEntityName": null, "associationEntityType": null, "associationEntityId": null, "rulesheetName": "COA Ordering", "ruleNumber": "8", "householdId": "77", "familyName": "Graveston", "personId": 273, "personName": "Marti Graveston", "coaName": "Pickle", "policyKey": "GA_PICKLE"}, {"sequence": 45890, "action": "Update Attribute", "element": "classOfAssistance (ClassOfAssistance) [2600]/priorityForGroup", "oldValue": "", "newValue": "2", "associationEntity": null, "location": "COA Ordering : 8", "entityName": "classOfAssistance", "entityType": "ClassOfAssistance", "entityId": 2600, "attributeName": "priorityForGroup", "associationEntityName": null, "associationEntityType": null, "associationEntityId": null, "rulesheetName": "COA Ordering", "ruleNumber": "8", "householdId": "77", "familyName": "Graveston", "personId": 273, "personName": "Marti Graveston", "coaName": "Pickle", "policyKey": "GA_PICKLE"}, {"sequence": 46362, "action": "Update Attribute", "element": "classOfAssistance (ClassOfAssistance) [265]/group", "oldValue": "", "newValue": "SSI and SSI-Derived", "associationEntity": null, "location": "COA Ordering : 11", "entityName": "classOfAssistance", "entityType": "ClassOfAssistance", "entityId": 265, "attributeName": "group", "associationEntityName": null, "associationEntityType": null, "associationEntityId": null, "rulesheetName": "COA Ordering", "ruleNumber": "11", "householdId": "77", "familyName": "Graveston", "personId": 273, "personName": "Marti Graveston", "coaName": "Protected Medicaid 1972", "policyKey": "GA_PROTECTED_MEDICAID_1972"}, {"sequence": 46363, "action": "Update Attribute", "element": "classOfAssistance (ClassOfAssistance) [265]/groupRank", "oldValue": "", "newValue": "20", "associationEntity": null, "location": "COA Ordering : 11", "entityName": "classOfAssistance", "entityType": "ClassOfAssistance", "entityId": 265, "attributeName": "groupRank", "associationEntityName": null, "associationEntityType": null, "associationEntityId": null, "rulesheetName": "COA Ordering", "ruleNumber": "11", "householdId": "77", "familyName": "Graveston", "personId": 273, "personName": "Marti Graveston", "coaName": "Protected Medicaid 1972", "policyKey": "GA_PROTECTED_MEDICAID_1972"}, {"sequence": 46364, "action": "Update Attribute", "element": "classOfAssistance (ClassOfAssistance) [265]/priorityForGroup", "oldValue": "", "newValue": "5", "associationEntity": null, "location": "COA Ordering : 11", "entityName": "classOfAssistance", "entityType": "ClassOfAssistance", "entityId": 265, "attributeName": "priorityForGroup", "associationEntityName": null, "associationEntityType": null, "associationEntityId": null, "rulesheetName": "COA Ordering", "ruleNumber": "11", "householdId": "77", "familyName": "Graveston", "personId": 273, "personName": "Marti Graveston", "coaName": "Protected Medicaid 1972", "policyKey": "GA_PROTECTED_MEDICAID_1972"}, {"sequence": 46482, "action": "Update Attribute", "element": "classOfAssistance (ClassOfAssistance) [463]/group", "oldValue": "", "newValue": "SSI and SSI-Derived", "associationEntity": null, "location": "COA Ordering : 12", "entityName": "classOfAssistance", "entityType": "ClassOfAssistance", "entityId": 463, "attributeName": "group", "associationEntityName": null, "associationEntityType": null, "associationEntityId": null, "rulesheetName": "COA Ordering", "ruleNumber": "12", "householdId": "77", "familyName": "Graveston", "personId": 273, "personName": "Marti Graveston", "coaName": "ABD Medically Needy", "policyKey": "GA_ABD_MED_NEEDY"}, {"sequence": 46483, "action": "Update Attribute", "element": "classOfAssistance (ClassOfAssistance) [463]/groupRank", "oldValue": "", "newValue": "20", "associationEntity": null, "location": "COA Ordering : 12", "entityName": "classOfAssistance", "entityType": "ClassOfAssistance", "entityId": 463, "attributeName": "groupRank", "associationEntityName": null, "associationEntityType": null, "associationEntityId": null, "rulesheetName": "COA Ordering", "ruleNumber": "12", "householdId": "77", "familyName": "Graveston", "personId": 273, "personName": "Marti Graveston", "coaName": "ABD Medically Needy", "policyKey": "GA_ABD_MED_NEEDY"}, {"sequence": 46484, "action": "Update Attribute", "element": "classOfAssistance (ClassOfAssistance) [463]/priorityForGroup", "oldValue": "", "newValue": "6", "associationEntity": null, "location": "COA Ordering : 12", "entityName": "classOfAssistance", "entityType": "ClassOfAssistance", "entityId": 463, "attributeName": "priorityForGroup", "associationEntityName": null, "associationEntityType": null, "associationEntityId": null, "rulesheetName": "COA Ordering", "ruleNumber": "12", "householdId": "77", "familyName": "Graveston", "personId": 273, "personName": "Marti Graveston", "coaName": "ABD Medically Needy", "policyKey": "GA_ABD_MED_NEEDY"}, {"sequence": 48411, "action": "Update Attribute", "element": "classOfAssistance (ClassOfAssistance) [1363]/group", "oldValue": "", "newValue": "Family (MAGI) & Overlaps", "associationEntity": null, "location": "COA Ordering : 19", "entityName": "classOfAssistance", "entityType": "ClassOfAssistance", "entityId": 1363, "attributeName": "group", "associationEntityName": null, "associationEntityType": null, "associationEntityId": null, "rulesheetName": "COA Ordering", "ruleNumber": "19", "householdId": "77", "familyName": "Graveston", "personId": 273, "personName": "Marti Graveston", "coaName": "Pregnant Women", "policyKey": "GA_PREGNANT_MEDICAID"}, {"sequence": 48412, "action": "Update Attribute", "element": "classOfAssistance (ClassOfAssistance) [1363]/groupRank", "oldValue": "", "newValue": "40", "associationEntity": null, "location": "COA Ordering : 19", "entityName": "classOfAssistance", "entityType": "ClassOfAssistance", "entityId": 1363, "attributeName": "groupRank", "associationEntityName": null, "associationEntityType": null, "associationEntityId": null, "rulesheetName": "COA Ordering", "ruleNumber": "19", "householdId": "77", "familyName": "Graveston", "personId": 273, "personName": "Marti Graveston", "coaName": "Pregnant Women", "policyKey": "GA_PREGNANT_MEDICAID"}, {"sequence": 48413, "action": "Update Attribute", "element": "classOfAssistance (ClassOfAssistance) [1363]/priorityForGroup", "oldValue": "", "newValue": "2", "associationEntity": null, "location": "COA Ordering : 19", "entityName": "classOfAssistance", "entityType": "ClassOfAssistance", "entityId": 1363, "attributeName": "priorityForGroup", "associationEntityName": null, "associationEntityType": null, "associationEntityId": null, "rulesheetName": "COA Ordering", "ruleNumber": "19", "householdId": "77", "familyName": "Graveston", "personId": 273, "personName": "Marti Graveston", "coaName": "Pregnant Women", "policyKey": "GA_PREGNANT_MEDICAID"}, {"sequence": 49794, "action": "Update Attribute", "element": "classOfAssistance (ClassOfAssistance) [2264]/group", "oldValue": "", "newValue": "Family (MAGI) & Overlaps", "associationEntity": null, "location": "COA Ordering : 25", "entityName": "classOfAssistance", "entityType": "ClassOfAssistance", "entityId": 2264, "attributeName": "group", "associationEntityName": null, "associationEntityType": null, "associationEntityId": null, "rulesheetName": "COA Ordering", "ruleNumber": "25", "householdId": "77", "familyName": "Graveston", "personId": 273, "personName": "Marti Graveston", "coaName": "Women's Health Medicaid", "policyKey": "GA_WOMENS_HEALTH"}, {"sequence": 49795, "action": "Update Attribute", "element": "classOfAssistance (ClassOfAssistance) [2264]/groupRank", "oldValue": "", "newValue": "40", "associationEntity": null, "location": "COA Ordering : 25", "entityName": "classOfAssistance", "entityType": "ClassOfAssistance", "entityId": 2264, "attributeName": "groupRank", "associationEntityName": null, "associationEntityType": null, "associationEntityId": null, "rulesheetName": "COA Ordering", "ruleNumber": "25", "householdId": "77", "familyName": "Graveston", "personId": 273, "personName": "Marti Graveston", "coaName": "Women's Health Medicaid", "policyKey": "GA_WOMENS_HEALTH"}, {"sequence": 49796, "action": "Update Attribute", "element": "classOfAssistance (ClassOfAssistance) [2264]/priorityForGroup", "oldValue": "", "newValue": "8", "associationEntity": null, "location": "COA Ordering : 25", "entityName": "classOfAssistance", "entityType": "ClassOfAssistance", "entityId": 2264, "attributeName": "priorityForGroup", "associationEntityName": null, "associationEntityType": null, "associationEntityId": null, "rulesheetName": "COA Ordering", "ruleNumber": "25", "householdId": "77", "familyName": "Graveston", "personId": 273, "personName": "Marti Graveston", "coaName": "Women's Health Medicaid", "policyKey": "GA_WOMENS_HEALTH"}, {"sequence": 50394, "action": "Update Attribute", "element": "classOfAssistance (ClassOfAssistance) [1726]/group", "oldValue": "", "newValue": "Family (MAGI) & Overlaps", "associationEntity": null, "location": "COA Ordering : 26", "entityName": "classOfAssistance", "entityType": "ClassOfAssistance", "entityId": 1726, "attributeName": "group", "associationEntityName": null, "associationEntityType": null, "associationEntityId": null, "rulesheetName": "COA Ordering", "ruleNumber": "26", "householdId": "77", "familyName": "Graveston", "personId": 273, "personName": "Marti Graveston", "coaName": "Pathways", "policyKey": "GA_PATHWAYS"}, {"sequence": 50395, "action": "Update Attribute", "element": "classOfAssistance (ClassOfAssistance) [1726]/groupRank", "oldValue": "", "newValue": "40", "associationEntity": null, "location": "COA Ordering : 26", "entityName": "classOfAssistance", "entityType": "ClassOfAssistance", "entityId": 1726, "attributeName": "groupRank", "associationEntityName": null, "associationEntityType": null, "associationEntityId": null, "rulesheetName": "COA Ordering", "ruleNumber": "26", "householdId": "77", "familyName": "Graveston", "personId": 273, "personName": "Marti Graveston", "coaName": "Pathways", "policyKey": "GA_PATHWAYS"}, {"sequence": 50396, "action": "Update Attribute", "element": "classOfAssistance (ClassOfAssistance) [1726]/priorityForGroup", "oldValue": "", "newValue": "9", "associationEntity": null, "location": "COA Ordering : 26", "entityName": "classOfAssistance", "entityType": "ClassOfAssistance", "entityId": 1726, "attributeName": "priorityForGroup", "associationEntityName": null, "associationEntityType": null, "associationEntityId": null, "rulesheetName": "COA Ordering", "ruleNumber": "26", "householdId": "77", "familyName": "Graveston", "personId": 273, "personName": "Marti Graveston", "coaName": "Pathways", "policyKey": "GA_PATHWAYS"}, {"sequence": 51282, "action": "Update Attribute", "element": "classOfAssistance (ClassOfAssistance) [1543]/group", "oldValue": "", "newValue": "Family (MAGI) & Overlaps", "associationEntity": null, "location": "COA Ordering : 27", "entityName": "classOfAssistance", "entityType": "ClassOfAssistance", "entityId": 1543, "attributeName": "group", "associationEntityName": null, "associationEntityType": null, "associationEntityId": null, "rulesheetName": "COA Ordering", "ruleNumber": "27", "householdId": "77", "familyName": "Graveston", "personId": 273, "personName": "Marti Graveston", "coaName": "Planning for Healthy Babies", "policyKey": "GA_PLANNING_HEALTHY_BABIES"}, {"sequence": 51283, "action": "Update Attribute", "element": "classOfAssistance (ClassOfAssistance) [1543]/groupRank", "oldValue": "", "newValue": "40", "associationEntity": null, "location": "COA Ordering : 27", "entityName": "classOfAssistance", "entityType": "ClassOfAssistance", "entityId": 1543, "attributeName": "groupRank", "associationEntityName": null, "associationEntityType": null, "associationEntityId": null, "rulesheetName": "COA Ordering", "ruleNumber": "27", "householdId": "77", "familyName": "Graveston", "personId": 273, "personName": "Marti Graveston", "coaName": "Planning for Healthy Babies", "policyKey": "GA_PLANNING_HEALTHY_BABIES"}, {"sequence": 51284, "action": "Update Attribute", "element": "classOfAssistance (ClassOfAssistance) [1543]/priorityForGroup", "oldValue": "", "newValue": "10", "associationEntity": null, "location": "COA Ordering : 27", "entityName": "classOfAssistance", "entityType": "ClassOfAssistance", "entityId": 1543, "attributeName": "priorityForGroup", "associationEntityName": null, "associationEntityType": null, "associationEntityId": null, "rulesheetName": "COA Ordering", "ruleNumber": "27", "householdId": "77", "familyName": "Graveston", "personId": 273, "personName": "Marti Graveston", "coaName": "Planning for Healthy Babies", "policyKey": "GA_PLANNING_HEALTHY_BABIES"}, {"sequence": 52056, "action": "Update Attribute", "element": "classOfAssistance (ClassOfAssistance) [1892]/group", "oldValue": "", "newValue": "Family (MAGI) & Overlaps", "associationEntity": null, "location": "COA Ordering : 28", "entityName": "classOfAssistance", "entityType": "ClassOfAssistance", "entityId": 1892, "attributeName": "group", "associationEntityName": null, "associationEntityType": null, "associationEntityId": null, "rulesheetName": "COA Ordering", "ruleNumber": "28", "householdId": "77", "familyName": "Graveston", "personId": 273, "personName": "Marti Graveston", "coaName": "Family Medicaid Medically Needy", "policyKey": "GA_FAMILY_MED_NEEDY"}, {"sequence": 52057, "action": "Update Attribute", "element": "classOfAssistance (ClassOfAssistance) [1892]/groupRank", "oldValue": "", "newValue": "40", "associationEntity": null, "location": "COA Ordering : 28", "entityName": "classOfAssistance", "entityType": "ClassOfAssistance", "entityId": 1892, "attributeName": "groupRank", "associationEntityName": null, "associationEntityType": null, "associationEntityId": null, "rulesheetName": "COA Ordering", "ruleNumber": "28", "householdId": "77", "familyName": "Graveston", "personId": 273, "personName": "Marti Graveston", "coaName": "Family Medicaid Medically Needy", "policyKey": "GA_FAMILY_MED_NEEDY"}, {"sequence": 52058, "action": "Update Attribute", "element": "classOfAssistance (ClassOfAssistance) [1892]/priorityForGroup", "oldValue": "", "newValue": "11", "associationEntity": null, "location": "COA Ordering : 28", "entityName": "classOfAssistance", "entityType": "ClassOfAssistance", "entityId": 1892, "attributeName": "priorityForGroup", "associationEntityName": null, "associationEntityType": null, "associationEntityId": null, "rulesheetName": "COA Ordering", "ruleNumber": "28", "householdId": "77", "familyName": "Graveston", "personId": 273, "personName": "Marti Graveston", "coaName": "Family Medicaid Medically Needy", "policyKey": "GA_FAMILY_MED_NEEDY"}, {"sequence": 53012, "action": "Update Attribute", "element": "classOfAssistance (ClassOfAssistance) [179]/globalPriority", "oldValue": "", "newValue": "2002", "associationEntity": null, "location": "coaPrioritization : 1", "entityName": "classOfAssistance", "entityType": "ClassOfAssistance", "entityId": 179, "attributeName": "globalPriority", "associationEntityName": null, "associationEntityType": null, "associationEntityId": null, "rulesheetName": "coaPrioritization", "ruleNumber": "1", "householdId": "77", "familyName": "Graveston", "personId": 273, "personName": "Marti Graveston", "coaName": "Pickle", "policyKey": "GA_PICKLE"}, {"sequence": 53018, "action": "Update Attribute", "element": "classOfAssistance (ClassOfAssistance) [2264]/globalPriority", "oldValue": "", "newValue": "4008", "associationEntity": null, "location": "coaPrioritization : 1", "entityName": "classOfAssistance", "entityType": "ClassOfAssistance", "entityId": 2264, "attributeName": "globalPriority", "associationEntityName": null, "associationEntityType": null, "associationEntityId": null, "rulesheetName": "coaPrioritization", "ruleNumber": "1", "householdId": "77", "familyName": "Graveston", "personId": 273, "personName": "Marti Graveston", "coaName": "Women's Health Medicaid", "policyKey": "GA_WOMENS_HEALTH"}, {"sequence": 53036, "action": "Update Attribute", "element": "classOfAssistance (ClassOfAssistance) [463]/globalPriority", "oldValue": "", "newValue": "2006", "associationEntity": null, "location": "coaPrioritization : 1", "entityName": "classOfAssistance", "entityType": "ClassOfAssistance", "entityId": 463, "attributeName": "globalPriority", "associationEntityName": null, "associationEntityType": null, "associationEntityId": null, "rulesheetName": "coaPrioritization", "ruleNumber": "1", "householdId": "77", "familyName": "Graveston", "personId": 273, "personName": "Marti Graveston", "coaName": "ABD Medically Needy", "policyKey": "GA_ABD_MED_NEEDY"}, {"sequence": 53318, "action": "Update Attribute", "element": "classOfAssistance (ClassOfAssistance) [29]/globalPriority", "oldValue": "", "newValue": "2001", "associationEntity": null, "location": "coaPrioritization : 1", "entityName": "classOfAssistance", "entityType": "ClassOfAssistance", "entityId": 29, "attributeName": "globalPriority", "associationEntityName": null, "associationEntityType": null, "associationEntityId": null, "rulesheetName": "coaPrioritization", "ruleNumber": "1", "householdId": "77", "familyName": "Graveston", "personId": 273, "personName": "Marti Graveston", "coaName": "Supplemental Security Income (SSI) Medicaid", "policyKey": "GA_SSI_MEDICAID"}, {"sequence": 53440, "action": "Update Attribute", "element": "classOfAssistance (ClassOfAssistance) [1726]/globalPriority", "oldValue": "", "newValue": "4009", "associationEntity": null, "location": "coaPrioritization : 1", "entityName": "classOfAssistance", "entityType": "ClassOfAssistance", "entityId": 1726, "attributeName": "globalPriority", "associationEntityName": null, "associationEntityType": null, "associationEntityId": null, "rulesheetName": "coaPrioritization", "ruleNumber": "1", "householdId": "77", "familyName": "Graveston", "personId": 273, "personName": "Marti Graveston", "coaName": "Pathways", "policyKey": "GA_PATHWAYS"}, {"sequence": 53875, "action": "Update Attribute", "element": "classOfAssistance (ClassOfAssistance) [2600]/globalPriority", "oldValue": "", "newValue": "2002", "associationEntity": null, "location": "coaPrioritization : 1", "entityName": "classOfAssistance", "entityType": "ClassOfAssistance", "entityId": 2600, "attributeName": "globalPriority", "associationEntityName": null, "associationEntityType": null, "associationEntityId": null, "rulesheetName": "coaPrioritization", "ruleNumber": "1", "householdId": "77", "familyName": "Graveston", "personId": 273, "personName": "Marti Graveston", "coaName": "Pickle", "policyKey": "GA_PICKLE"}, {"sequence": 53962, "action": "Update Attribute", "element": "classOfAssistance (ClassOfAssistance) [2450]/globalPriority", "oldValue": "", "newValue": "2001", "associationEntity": null, "location": "coaPrioritization : 1", "entityName": "classOfAssistance", "entityType": "ClassOfAssistance", "entityId": 2450, "attributeName": "globalPriority", "associationEntityName": null, "associationEntityType": null, "associationEntityId": null, "rulesheetName": "coaPrioritization", "ruleNumber": "1", "householdId": "77", "familyName": "Graveston", "personId": 273, "personName": "Marti Graveston", "coaName": "Supplemental Security Income (SSI) Medicaid", "policyKey": "GA_SSI_MEDICAID"}, {"sequence": 54256, "action": "Update Attribute", "element": "classOfAssistance (ClassOfAssistance) [1892]/globalPriority", "oldValue": "", "newValue": "4011", "associationEntity": null, "location": "coaPrioritization : 1", "entityName": "classOfAssistance", "entityType": "ClassOfAssistance", "entityId": 1892, "attributeName": "globalPriority", "associationEntityName": null, "associationEntityType": null, "associationEntityId": null, "rulesheetName": "coaPrioritization", "ruleNumber": "1", "householdId": "77", "familyName": "Graveston", "personId": 273, "personName": "Marti Graveston", "coaName": "Family Medicaid Medically Needy", "policyKey": "GA_FAMILY_MED_NEEDY"}, {"sequence": 54868, "action": "Update Attribute", "element": "classOfAssistance (ClassOfAssistance) [265]/globalPriority", "oldValue": "", "newValue": "2005", "associationEntity": null, "location": "coaPrioritization : 1", "entityName": "classOfAssistance", "entityType": "ClassOfAssistance", "entityId": 265, "attributeName": "globalPriority", "associationEntityName": null, "associationEntityType": null, "associationEntityId": null, "rulesheetName": "coaPrioritization", "ruleNumber": "1", "householdId": "77", "familyName": "Graveston", "personId": 273, "personName": "Marti Graveston", "coaName": "Protected Medicaid 1972", "policyKey": "GA_PROTECTED_MEDICAID_1972"}, {"sequence": 55111, "action": "Update Attribute", "element": "classOfAssistance (ClassOfAssistance) [1363]/globalPriority", "oldValue": "", "newValue": "4002", "associationEntity": null, "location": "coaPrioritization : 1", "entityName": "classOfAssistance", "entityType": "ClassOfAssistance", "entityId": 1363, "attributeName": "globalPriority", "associationEntityName": null, "associationEntityType": null, "associationEntityId": null, "rulesheetName": "coaPrioritization", "ruleNumber": "1", "householdId": "77", "familyName": "Graveston", "personId": 273, "personName": "Marti Graveston", "coaName": "Pregnant Women", "policyKey": "GA_PREGNANT_MEDICAID"}, {"sequence": 55134, "action": "Update Attribute", "element": "classOfAssistance (ClassOfAssistance) [1543]/globalPriority", "oldValue": "", "newValue": "4010", "associationEntity": null, "location": "coaPrioritization : 1", "entityName": "classOfAssistance", "entityType": "ClassOfAssistance", "entityId": 1543, "attributeName": "globalPriority", "associationEntityName": null, "associationEntityType": null, "associationEntityId": null, "rulesheetName": "coaPrioritization", "ruleNumber": "1", "householdId": "77", "familyName": "Graveston", "personId": 273, "personName": "Marti Graveston", "coaName": "Planning for Healthy Babies", "policyKey": "GA_PLANNING_HEALTHY_BABIES"}, {"sequence": 55552, "action": "Update Attribute", "element": "classOfAssistance (ClassOfAssistance) [2264]/eligibleViaPath", "oldValue": "", "newValue": "false", "associationEntity": null, "location": "COA Eligibility : A0", "entityName": "classOfAssistance", "entityType": "ClassOfAssistance", "entityId": 2264, "attributeName": "eligibleViaPath", "associationEntityName": null, "associationEntityType": null, "associationEntityId": null, "rulesheetName": "COA Eligibility", "ruleNumber": "A0", "householdId": "77", "familyName": "Graveston", "personId": 273, "personName": "Marti Graveston", "coaName": "Women's Health Medicaid", "policyKey": "GA_WOMENS_HEALTH"}, {"sequence": 55553, "action": "Update Attribute", "element": "classOfAssistance (ClassOfAssistance) [1363]/eligibleViaPath", "oldValue": "", "newValue": "false", "associationEntity": null, "location": "COA Eligibility : A0", "entityName": "classOfAssistance", "entityType": "ClassOfAssistance", "entityId": 1363, "attributeName": "eligibleViaPath", "associationEntityName": null, "associationEntityType": null, "associationEntityId": null, "rulesheetName": "COA Eligibility", "ruleNumber": "A0", "householdId": "77", "familyName": "Graveston", "personId": 273, "personName": "Marti Graveston", "coaName": "Pregnant Women", "policyKey": "GA_PREGNANT_MEDICAID"}, {"sequence": 55554, "action": "Update Attribute", "element": "classOfAssistance (ClassOfAssistance) [29]/eligibleViaPath", "oldValue": "", "newValue": "false", "associationEntity": null, "location": "COA Eligibility : A0", "entityName": "classOfAssistance", "entityType": "ClassOfAssistance", "entityId": 29, "attributeName": "eligibleViaPath", "associationEntityName": null, "associationEntityType": null, "associationEntityId": null, "rulesheetName": "COA Eligibility", "ruleNumber": "A0", "householdId": "77", "familyName": "Graveston", "personId": 273, "personName": "Marti Graveston", "coaName": "Supplemental Security Income (SSI) Medicaid", "policyKey": "GA_SSI_MEDICAID"}, {"sequence": 55555, "action": "Update Attribute", "element": "classOfAssistance (ClassOfAssistance) [463]/eligibleViaPath", "oldValue": "", "newValue": "false", "associationEntity": null, "location": "COA Eligibility : A0", "entityName": "classOfAssistance", "entityType": "ClassOfAssistance", "entityId": 463, "attributeName": "eligibleViaPath", "associationEntityName": null, "associationEntityType": null, "associationEntityId": null, "rulesheetName": "COA Eligibility", "ruleNumber": "A0", "householdId": "77", "familyName": "Graveston", "personId": 273, "personName": "Marti Graveston", "coaName": "ABD Medically Needy", "policyKey": "GA_ABD_MED_NEEDY"}, {"sequence": 55556, "action": "Update Attribute", "element": "classOfAssistance (ClassOfAssistance) [1543]/eligibleViaPath", "oldValue": "", "newValue": "false", "associationEntity": null, "location": "COA Eligibility : A0", "entityName": "classOfAssistance", "entityType": "ClassOfAssistance", "entityId": 1543, "attributeName": "eligibleViaPath", "associationEntityName": null, "associationEntityType": null, "associationEntityId": null, "rulesheetName": "COA Eligibility", "ruleNumber": "A0", "householdId": "77", "familyName": "Graveston", "personId": 273, "personName": "Marti Graveston", "coaName": "Planning for Healthy Babies", "policyKey": "GA_PLANNING_HEALTHY_BABIES"}, {"sequence": 55557, "action": "Update Attribute", "element": "classOfAssistance (ClassOfAssistance) [1892]/eligibleViaPath", "oldValue": "", "newValue": "false", "associationEntity": null, "location": "COA Eligibility : A0", "entityName": "classOfAssistance", "entityType": "ClassOfAssistance", "entityId": 1892, "attributeName": "eligibleViaPath", "associationEntityName": null, "associationEntityType": null, "associationEntityId": null, "rulesheetName": "COA Eligibility", "ruleNumber": "A0", "householdId": "77", "familyName": "Graveston", "personId": 273, "personName": "Marti Graveston", "coaName": "Family Medicaid Medically Needy", "policyKey": "GA_FAMILY_MED_NEEDY"}, {"sequence": 55558, "action": "Update Attribute", "element": "classOfAssistance (ClassOfAssistance) [265]/eligibleViaPath", "oldValue": "", "newValue": "false", "associationEntity": null, "location": "COA Eligibility : A0", "entityName": "classOfAssistance", "entityType": "ClassOfAssistance", "entityId": 265, "attributeName": "eligibleViaPath", "associationEntityName": null, "associationEntityType": null, "associationEntityId": null, "rulesheetName": "COA Eligibility", "ruleNumber": "A0", "householdId": "77", "familyName": "Graveston", "personId": 273, "personName": "Marti Graveston", "coaName": "Protected Medicaid 1972", "policyKey": "GA_PROTECTED_MEDICAID_1972"}, {"sequence": 55559, "action": "Update Attribute", "element": "classOfAssistance (ClassOfAssistance) [179]/eligibleViaPath", "oldValue": "", "newValue": "false", "associationEntity": null, "location": "COA Eligibility : A0", "entityName": "classOfAssistance", "entityType": "ClassOfAssistance", "entityId": 179, "attributeName": "eligibleViaPath", "associationEntityName": null, "associationEntityType": null, "associationEntityId": null, "rulesheetName": "COA Eligibility", "ruleNumber": "A0", "householdId": "77", "familyName": "Graveston", "personId": 273, "personName": "Marti Graveston", "coaName": "Pickle", "policyKey": "GA_PICKLE"}, {"sequence": 55560, "action": "Update Attribute", "element": "classOfAssistance (ClassOfAssistance) [2450]/eligibleViaPath", "oldValue": "", "newValue": "false", "associationEntity": null, "location": "COA Eligibility : A0", "entityName": "classOfAssistance", "entityType": "ClassOfAssistance", "entityId": 2450, "attributeName": "eligibleViaPath", "associationEntityName": null, "associationEntityType": null, "associationEntityId": null, "rulesheetName": "COA Eligibility", "ruleNumber": "A0", "householdId": "77", "familyName": "Graveston", "personId": 273, "personName": "Marti Graveston", "coaName": "Supplemental Security Income (SSI) Medicaid", "policyKey": "GA_SSI_MEDICAID"}, {"sequence": 55561, "action": "Update Attribute", "element": "classOfAssistance (ClassOfAssistance) [2600]/eligibleViaPath", "oldValue": "", "newValue": "false", "associationEntity": null, "location": "COA Eligibility : A0", "entityName": "classOfAssistance", "entityType": "ClassOfAssistance", "entityId": 2600, "attributeName": "eligibleViaPath", "associationEntityName": null, "associationEntityType": null, "associationEntityId": null, "rulesheetName": "COA Eligibility", "ruleNumber": "A0", "householdId": "77", "familyName": "Graveston", "personId": 273, "personName": "Marti Graveston", "coaName": "Pickle", "policyKey": "GA_PICKLE"}, {"sequence": 55562, "action": "Update Attribute", "element": "classOfAssistance (ClassOfAssistance) [1726]/eligibleViaPath", "oldValue": "", "newValue": "false", "associationEntity": null, "location": "COA Eligibility : A0", "entityName": "classOfAssistance", "entityType": "ClassOfAssistance", "entityId": 1726, "attributeName": "eligibleViaPath", "associationEntityName": null, "associationEntityType": null, "associationEntityId": null, "rulesheetName": "COA Eligibility", "ruleNumber": "A0", "householdId": "77", "familyName": "Graveston", "personId": 273, "personName": "Marti Graveston", "coaName": "Pathways", "policyKey": "GA_PATHWAYS"}, {"sequence": 58218, "action": "Update Attribute", "element": "classOfAssistance (ClassOfAssistance) [2264]/eligibleViaPath", "oldValue": "false", "newValue": "true", "associationEntity": null, "location": "COA Eligibility : 1", "entityName": "classOfAssistance", "entityType": "ClassOfAssistance", "entityId": 2264, "attributeName": "eligibleViaPath", "associationEntityName": null, "associationEntityType": null, "associationEntityId": null, "rulesheetName": "COA Eligibility", "ruleNumber": "1", "householdId": "77", "familyName": "Graveston", "personId": 273, "personName": "Marti Graveston", "coaName": "Women's Health Medicaid", "policyKey": "GA_WOMENS_HEALTH"}, {"sequence": 58219, "action": "Update Attribute", "element": "classOfAssistance (ClassOfAssistance) [1363]/eligibleViaPath", "oldValue": "false", "newValue": "true", "associationEntity": null, "location": "COA Eligibility : 1", "entityName": "classOfAssistance", "entityType": "ClassOfAssistance", "entityId": 1363, "attributeName": "eligibleViaPath", "associationEntityName": null, "associationEntityType": null, "associationEntityId": null, "rulesheetName": "COA Eligibility", "ruleNumber": "1", "householdId": "77", "familyName": "Graveston", "personId": 273, "personName": "Marti Graveston", "coaName": "Pregnant Women", "policyKey": "GA_PREGNANT_MEDICAID"}, {"sequence": 58220, "action": "Update Attribute", "element": "classOfAssistance (ClassOfAssistance) [29]/eligibleViaPath", "oldValue": "false", "newValue": "true", "associationEntity": null, "location": "COA Eligibility : 1", "entityName": "classOfAssistance", "entityType": "ClassOfAssistance", "entityId": 29, "attributeName": "eligibleViaPath", "associationEntityName": null, "associationEntityType": null, "associationEntityId": null, "rulesheetName": "COA Eligibility", "ruleNumber": "1", "householdId": "77", "familyName": "Graveston", "personId": 273, "personName": "Marti Graveston", "coaName": "Supplemental Security Income (SSI) Medicaid", "policyKey": "GA_SSI_MEDICAID"}, {"sequence": 58221, "action": "Update Attribute", "element": "classOfAssistance (ClassOfAssistance) [463]/eligibleViaPath", "oldValue": "false", "newValue": "true", "associationEntity": null, "location": "COA Eligibility : 1", "entityName": "classOfAssistance", "entityType": "ClassOfAssistance", "entityId": 463, "attributeName": "eligibleViaPath", "associationEntityName": null, "associationEntityType": null, "associationEntityId": null, "rulesheetName": "COA Eligibility", "ruleNumber": "1", "householdId": "77", "familyName": "Graveston", "personId": 273, "personName": "Marti Graveston", "coaName": "ABD Medically Needy", "policyKey": "GA_ABD_MED_NEEDY"}, {"sequence": 58222, "action": "Update Attribute", "element": "classOfAssistance (ClassOfAssistance) [1543]/eligibleViaPath", "oldValue": "false", "newValue": "true", "associationEntity": null, "location": "COA Eligibility : 1", "entityName": "classOfAssistance", "entityType": "ClassOfAssistance", "entityId": 1543, "attributeName": "eligibleViaPath", "associationEntityName": null, "associationEntityType": null, "associationEntityId": null, "rulesheetName": "COA Eligibility", "ruleNumber": "1", "householdId": "77", "familyName": "Graveston", "personId": 273, "personName": "Marti Graveston", "coaName": "Planning for Healthy Babies", "policyKey": "GA_PLANNING_HEALTHY_BABIES"}, {"sequence": 58223, "action": "Update Attribute", "element": "classOfAssistance (ClassOfAssistance) [1892]/eligibleViaPath", "oldValue": "false", "newValue": "true", "associationEntity": null, "location": "COA Eligibility : 1", "entityName": "classOfAssistance", "entityType": "ClassOfAssistance", "entityId": 1892, "attributeName": "eligibleViaPath", "associationEntityName": null, "associationEntityType": null, "associationEntityId": null, "rulesheetName": "COA Eligibility", "ruleNumber": "1", "householdId": "77", "familyName": "Graveston", "personId": 273, "personName": "Marti Graveston", "coaName": "Family Medicaid Medically Needy", "policyKey": "GA_FAMILY_MED_NEEDY"}, {"sequence": 58224, "action": "Update Attribute", "element": "classOfAssistance (ClassOfAssistance) [265]/eligibleViaPath", "oldValue": "false", "newValue": "true", "associationEntity": null, "location": "COA Eligibility : 1", "entityName": "classOfAssistance", "entityType": "ClassOfAssistance", "entityId": 265, "attributeName": "eligibleViaPath", "associationEntityName": null, "associationEntityType": null, "associationEntityId": null, "rulesheetName": "COA Eligibility", "ruleNumber": "1", "householdId": "77", "familyName": "Graveston", "personId": 273, "personName": "Marti Graveston", "coaName": "Protected Medicaid 1972", "policyKey": "GA_PROTECTED_MEDICAID_1972"}, {"sequence": 58225, "action": "Update Attribute", "element": "classOfAssistance (ClassOfAssistance) [179]/eligibleViaPath", "oldValue": "false", "newValue": "true", "associationEntity": null, "location": "COA Eligibility : 1", "entityName": "classOfAssistance", "entityType": "ClassOfAssistance", "entityId": 179, "attributeName": "eligibleViaPath", "associationEntityName": null, "associationEntityType": null, "associationEntityId": null, "rulesheetName": "COA Eligibility", "ruleNumber": "1", "householdId": "77", "familyName": "Graveston", "personId": 273, "personName": "Marti Graveston", "coaName": "Pickle", "policyKey": "GA_PICKLE"}, {"sequence": 58226, "action": "Update Attribute", "element": "classOfAssistance (ClassOfAssistance) [2450]/eligibleViaPath", "oldValue": "false", "newValue": "true", "associationEntity": null, "location": "COA Eligibility : 1", "entityName": "classOfAssistance", "entityType": "ClassOfAssistance", "entityId": 2450, "attributeName": "eligibleViaPath", "associationEntityName": null, "associationEntityType": null, "associationEntityId": null, "rulesheetName": "COA Eligibility", "ruleNumber": "1", "householdId": "77", "familyName": "Graveston", "personId": 273, "personName": "Marti Graveston", "coaName": "Supplemental Security Income (SSI) Medicaid", "policyKey": "GA_SSI_MEDICAID"}, {"sequence": 58227, "action": "Update Attribute", "element": "classOfAssistance (ClassOfAssistance) [2600]/eligibleViaPath", "oldValue": "false", "newValue": "true", "associationEntity": null, "location": "COA Eligibility : 1", "entityName": "classOfAssistance", "entityType": "ClassOfAssistance", "entityId": 2600, "attributeName": "eligibleViaPath", "associationEntityName": null, "associationEntityType": null, "associationEntityId": null, "rulesheetName": "COA Eligibility", "ruleNumber": "1", "householdId": "77", "familyName": "Graveston", "personId": 273, "personName": "Marti Graveston", "coaName": "Pickle", "policyKey": "GA_PICKLE"}, {"sequence": 58228, "action": "Update Attribute", "element": "classOfAssistance (ClassOfAssistance) [1726]/eligibleViaPath", "oldValue": "false", "newValue": "true", "associationEntity": null, "location": "COA Eligibility : 1", "entityName": "classOfAssistance", "entityType": "ClassOfAssistance", "entityId": 1726, "attributeName": "eligibleViaPath", "associationEntityName": null, "associationEntityType": null, "associationEntityId": null, "rulesheetName": "COA Eligibility", "ruleNumber": "1", "householdId": "77", "familyName": "Graveston", "personId": 273, "personName": "Marti Graveston", "coaName": "Pathways", "policyKey": "GA_PATHWAYS"}, {"sequence": 60562, "action": "Update Attribute", "element": "classOfAssistance (ClassOfAssistance) [29]/isSelected", "oldValue": "", "newValue": "true", "associationEntity": null, "location": "coaSelection : B0", "entityName": "classOfAssistance", "entityType": "ClassOfAssistance", "entityId": 29, "attributeName": "isSelected", "associationEntityName": null, "associationEntityType": null, "associationEntityId": null, "rulesheetName": "coaSelection", "ruleNumber": "B0", "householdId": "77", "familyName": "Graveston", "personId": 273, "personName": "Marti Graveston", "coaName": "Supplemental Security Income (SSI) Medicaid", "policyKey": "GA_SSI_MEDICAID"}], "rowCount": 144}